<?xml version="1.0" encoding="UTF-8"?>

<!-- generated on 2024-10-22 07:41:25 by Eclipse SUMO polyconvert Version 1.21.0
<polyconvertConfiguration xmlns:xsi="http://www.w3.org/2001/XMLSchema-instance" xsi:noNamespaceSchemaLocation="http://sumo.dlr.de/xsd/polyconvertConfiguration.xsd">

    <input>
        <net-file value="baripada.net.xml"/>
        <osm-files value="map.osm"/>
        <type-file value="typemap.xml"/>
    </input>

    <output>
        <output-file value="bpd.poly.xml"/>
    </output>

</polyconvertConfiguration>
-->

<additional xmlns:xsi="http://www.w3.org/2001/XMLSchema-instance" xsi:noNamespaceSchemaLocation="http://sumo.dlr.de/xsd/additional_file.xsd">
    <location netOffset="-469565.05,-2390336.47" convBoundary="-52348.16,-12639.70,32472.55,70724.89" origBoundary="86.196585,21.501852,87.019689,22.253096" projParameter="+proj=utm +zone=45 +ellps=WGS84 +datum=WGS84 +units=m +no_defs"/>

    <poly id="1086486815" type="university" color="237,199,199" fill="1" layer="-2.00" shape="6192.049810,34627.706564 6209.086970,34794.650282 6216.278176,34965.804093 6236.228673,34991.895500 6265.036747,35029.573308 6292.747846,35065.824991 6302.425926,35141.475197 6545.212495,35099.909852 6585.252096,35066.809753 6722.514083,35042.872618 6699.043073,34851.454272 6717.419522,34847.508468 6706.794757,34807.400724 6814.831325,34803.011081 6808.839186,34759.874641 6813.170269,34714.055280 6800.727957,34680.801649 6746.179234,34694.586031 6728.374097,34555.923212 6634.377314,34599.065606 6515.002600,34598.348819 6443.632054,34599.441831 6285.667596,34614.591204 6192.049810,34627.706564"/>
    <poly id="1086486826" type="building" color="255,230,230" fill="1" layer="-1.00" shape="6471.885755,34803.039073 6504.662775,34802.037631 6502.751192,34739.812878 6497.140018,34737.508018 6497.106453,34728.963114 6492.672394,34726.534723 6492.870993,34721.276841 6478.102185,34720.723599 6477.764649,34729.711808 6473.552732,34730.769694 6472.538172,34735.951331 6469.909318,34738.988102 6471.885755,34803.039073"/>
    <poly id="1106483689" type="leisure" color="207,245,201" fill="1" layer="-2.00" shape="6751.025376,34544.366935 6828.458333,34716.556133 6890.243917,34673.263483 6876.187867,34652.010546 6898.536136,34638.108387 6912.312559,34658.841535 6966.911192,34615.825510 6922.277327,34477.180125 6865.978632,34495.327704 6837.439415,34506.095643 6751.025376,34544.366935"/>
    <poly id="1106483691" type="water" color="181,209,209" fill="1" layer="-4.00" shape="6830.216123,34745.730322 7098.162041,34861.874570 7115.647189,34701.365331 7177.794268,34643.462743 7134.683680,34605.328384 7103.165409,34605.817509 7083.551300,34618.121470 7056.314689,34608.764403 7039.702328,34604.682477 7001.654715,34610.483301 6970.849939,34632.500041 6832.196846,34730.452714 6830.216123,34745.730322"/>
    <poly id="1106484825" type="college" color="237,199,199" fill="1" layer="-2.00" shape="6192.153490,34627.972052 6131.092535,34637.617796 6077.885438,34643.820436 6044.821330,34646.372803 5988.656558,34649.901696 5931.773265,34656.254392 5883.902705,34660.645252 5827.473269,34666.599150 5814.639036,34668.268310 5769.146207,34674.194357 5717.142608,34683.783330 5640.382634,34692.127240 5548.937303,34707.013988 5532.574360,34743.543947 5537.377381,34803.229372 5567.197091,34813.033593 5650.459893,34809.571469 5681.783810,34909.682279 5734.240487,34899.738278 5743.737802,34904.018090 5726.310264,34999.711199 5731.171546,35017.800784 5746.070150,35048.780717 5787.130587,35082.033274 5800.138958,35092.948820 5811.351621,35104.641970 5832.840261,35116.739771 5895.332049,35118.745873 5956.272707,35099.370076 5994.036265,35084.479838 6022.067543,35080.208407 6046.059137,35068.040263 6078.637679,35072.650019 6123.129736,35068.021409 6164.732171,35064.648102 6178.032131,35070.571570 6192.238104,35101.685797 6204.654709,35090.498581 6248.881094,35047.152766 6265.036747,35029.573308 6236.228673,34991.895500 6216.278176,34965.804093 6209.086970,34794.650282 6192.153490,34627.972052"/>
    <poly id="1106486033" type="tourism" color="207,245,201" fill="1" layer="-2.00" shape="5547.405288,34691.586764 5530.364777,34579.577164 5594.904276,34575.457949 5597.626226,34552.840534 5650.574098,34545.884024 5713.430178,34528.385992 5737.296734,34521.740820 5762.150446,34664.874421 5707.551670,34672.541530 5690.360506,34674.959187 5547.405288,34691.586764"/>
    <poly id="1106486035" type="college" color="237,199,199" fill="1" layer="-2.00" shape="6106.642687,34620.842122 6084.496960,34463.713157 6295.788298,34431.512314 6306.914682,34528.910054 6388.385462,34527.646137 6392.514220,34587.454549 6246.374639,34602.708128 6106.642687,34620.842122"/>
    <poly id="1106486254" type="water" color="181,209,209" fill="1" layer="-4.00" shape="7117.504617,34861.746472 7128.547497,34772.628067 7147.193644,34776.386106 7142.705559,34793.327647 7159.614124,34809.385458 7180.089070,34813.782827 7187.938451,34828.348641 7196.396505,34828.413712 7198.336318,34841.338981 7182.033787,34851.147535 7158.750703,34854.325205 7132.442645,34851.076508 7128.680058,34862.737270 7117.504617,34861.746472"/>
    <poly id="1106486702" type="water" color="181,209,209" fill="0" layer="-4.00" shape="4184.792322,47613.405568 4218.392590,47422.468694 4299.662289,46929.541221 4319.438163,46844.854553 4408.131151,46637.578142 4545.910670,46338.539117 4653.321869,46101.237229 4720.076776,46010.165220 4800.373355,45957.856365 4943.803554,45915.573606 5264.565200,45842.535770 5420.025612,45803.492381 5482.879070,45793.309148 5558.486189,45755.710913 5583.081052,45737.452982 5680.747066,45617.192484 5832.961269,45407.113214 5957.645109,45237.202352 6023.609403,45128.194901 6042.012379,45069.181190 6047.159113,45007.055554 6022.099613,44846.254723 5995.452404,44626.913960 5967.674564,44417.691847 5934.377868,44150.987493 5929.352112,44031.785262 5964.525824,43938.067231 6026.631475,43853.118299 6462.817001,43559.272786 6588.611122,43474.594793 6720.830712,43392.642138 6882.964551,43276.620771 6925.427222,43241.536108 6956.512513,43183.589494 6979.477851,43044.344395 7000.489978,42910.171716 7030.807277,42716.502160 7060.732298,42557.146216 7081.027846,42440.031633 7119.037463,42176.607232 7140.940931,42064.227805 7142.495172,42012.224860 7124.850442,41897.900387 7085.001904,41707.068867 7042.967539,41518.631549 6992.988034,41305.401268 6985.807229,41238.535019 6995.343814,41174.665711 7095.528613,40874.014144 7196.038822,40588.427322 7250.422527,40440.625106 7263.401971,40407.322614 7283.154109,40226.298990 7325.145279,39862.477320 7330.930500,39794.474144 7344.894168,39734.771582 7354.319340,39698.995013 7391.889609,39636.103488 7503.483234,39458.920365 7742.699440,39088.749773 7790.227652,38998.538652 7807.700670,38929.212907 7789.888210,38862.439189 7740.192205,38744.551990 7670.559973,38599.010987 7617.522147,38477.509558 7516.927863,38263.864388 7428.863735,38063.185153 7361.205494,37915.838503 7353.139216,37878.858920 7351.164310,37841.560531 7362.671026,37802.117301 7387.483671,37753.257432 7463.852710,37648.891005 7633.317295,37430.361622 7775.455892,37241.537146 7884.304081,37100.854543 7959.237034,36998.651074 7979.274554,36944.342164 7994.252960,36868.467736 7993.054203,36794.962803 7974.261098,36722.202291 7929.662504,36532.748948 7906.231837,36466.857661 7793.333080,36305.594193 7687.482359,36171.306661 7571.391328,36004.902470 7489.106790,35902.570517 7453.706178,35844.644521 7441.665813,35802.213916 7431.889673,35747.471749 7437.857177,35661.271899 7455.600781,35598.907797 7491.870743,35529.477244 7522.481011,35466.530098 7591.985668,35327.186782 7666.999041,35168.532263 7705.736665,35097.416280 7718.640064,35050.478019 7722.779568,34977.308711 7710.657770,34906.841326 7646.097689,34723.715744 7572.431485,34529.103324 7509.583685,34360.951664 7431.509982,34156.041470 7400.377122,34067.039964 7388.968060,34026.501275 7380.378435,33971.779645 7385.016795,33915.799098 7412.206547,33700.243327 7439.748099,33513.078039 7454.944114,33444.231622 7479.453539,33387.790673 7533.065297,33329.569934 7589.905786,33289.807104 7745.601351,33223.670195 7952.376734,33146.692604 8086.161958,33097.657887 8148.704509,33064.264549 8243.971095,32974.398106 8359.643342,32866.528495 8526.110576,32712.190112 8575.852710,32652.140971 8604.573695,32597.577713 8609.670043,32548.193884 8601.372225,32477.831450 8590.932545,32457.247251 8565.330344,32406.754597 8510.586967,32293.930958 8472.808072,32214.710270 8394.758320,32122.053018 8321.169594,32044.077894 8223.373010,31939.539268 8171.506524,31884.944416 8151.331463,31839.148956 8145.197123,31744.399746 8145.449674,31622.722872 8140.202330,31497.699974 8140.576539,31440.563630 8159.548794,31394.414369 8188.254457,31357.748294 8271.711780,31302.775820 8383.821678,31231.471064 8550.818950,31134.146681 8585.949755,31111.584872 8614.009574,31077.410903 8637.836068,31021.913734 8639.825664,30958.809293 8636.140785,30787.883013 8636.309871,30753.050114 8650.623101,30712.574985 8672.128841,30681.708560 8810.068769,30511.142186 9022.054362,30253.832630 9142.099331,30098.579065 9205.353278,30022.719283 9216.606918,29994.756232 9235.292290,29931.242260 9259.172294,29866.448507 9289.710182,29820.838734 9329.688138,29789.162801 9371.033299,29767.856356 9438.190290,29751.242123 9538.729146,29753.334272 9842.432297,29759.633969 9926.338957,29737.709346 9979.017949,29700.650440 10035.066432,29624.548757 10088.692165,29535.754810 10154.402002,29428.140233 10220.825492,29328.593979 10283.411336,29216.368388 10305.922455,29183.986616 10329.869534,29159.671996 10373.176313,29135.034101 10430.330666,29097.218435 10516.432028,29050.788567 10579.941952,29014.094467 10668.689515,28959.836703 10823.764184,28873.265969 10980.841292,28783.860785 11137.760307,28698.940109 11264.965132,28619.812445 11317.960042,28590.649537 11353.839175,28546.675582 11396.830068,28471.258692 11462.232413,28345.918427 11519.513942,28245.492206 11571.740486,28150.728201 11629.493845,28028.762591 11694.072943,27911.847458 11764.881491,27784.830842 11830.099494,27664.783181 11895.799090,27540.451752 11970.319052,27403.636208 12045.753290,27261.141864 12137.526132,27102.513414 12204.347091,26987.822717 12292.705848,26831.601008 12374.179734,26670.794239 12397.334874,26607.135398 12397.470378,26517.082286 12392.832928,26409.435755 12390.231153,26274.636013 12385.260160,26109.898821 12381.942904,25954.756126 12381.181567,25802.886818 12388.181272,25751.986158 12396.500339,25734.610331 12416.395406,25719.833547 12447.277177,25716.500202 12528.452923,25715.744517"/>
    <poly id="1106494319" type="building" color="255,230,230" fill="1" layer="-1.00" shape="6574.879215,34830.665798 6613.164876,34825.660522 6607.826920,34785.257110 6597.078416,34786.667922 6598.070723,34794.126662 6583.047591,34796.086276 6582.013368,34788.229131 6569.499253,34789.863992 6574.879215,34830.665798"/>
    <poly id="1106494320" type="building" color="255,230,230" fill="1" layer="-1.00" shape="6641.316097,34832.082277 6697.063690,34826.176568 6690.664398,34766.537506 6670.064858,34768.715699 6669.897298,34767.166348 6652.932369,34768.962779 6652.450613,34771.376456 6635.000395,34773.228979 6641.316097,34832.082277"/>
    <poly id="1106494323" type="building" color="255,230,230" fill="1" layer="-1.00" shape="6553.030155,34640.994085 6551.589756,34624.039172 6586.160350,34620.544766 6587.394466,34637.699227 6553.030155,34640.994085"/>
    <poly id="1106494324" type="building" color="255,230,230" fill="1" layer="-1.00" shape="6645.110264,34800.420399 6684.255630,34797.052156 6682.269708,34774.320242 6670.725383,34775.322659 6671.681610,34786.290201 6655.118897,34787.709695 6654.267724,34777.937405 6643.229369,34778.894808 6645.110264,34800.420399"/>
    <poly id="1106494956" type="water" color="181,209,209" fill="1" layer="-4.00" shape="1949.358070,35325.216716 1923.895922,35189.738114 1979.144621,35166.361422 2036.441620,35156.396440 2049.887413,35231.329150 2051.110921,35326.284803 1949.358070,35325.216716"/>
    <poly id="1106494957" type="water" color="181,209,209" fill="1" layer="-4.00" shape="1999.765545,35481.570299 2098.529164,35445.896161 2076.258130,35373.104375 2060.290219,35360.138391 1987.637382,35369.820948 1969.688735,35386.755008 1999.765545,35481.570299"/>
    <poly id="1106495599" type="college" color="237,199,199" fill="1" layer="-2.00" shape="1758.768499,35167.544717 1713.912434,35169.994674 1687.100844,35185.583681 1598.877499,35179.999417 1589.633321,35207.521821 1543.039514,35208.359407 1562.009712,35315.745990 1639.330361,35294.718705 1631.436536,35275.451483 1619.599431,35274.111570 1631.814860,35227.944186 1696.367883,35233.173088 1702.151043,35267.364696 1680.738004,35270.137508 1679.547268,35313.916147 1768.558213,35292.923619 1758.768499,35167.544717"/>
    <poly id="1128435236" type="water" color="181,209,209" fill="1" layer="-4.00" shape="2077.273238,36407.002569 2038.622550,36338.058807 2120.410555,36282.668689 2141.980873,36380.189208 2077.273238,36407.002569"/>
    <poly id="1128435239" type="leisure" color="207,245,201" fill="1" layer="-2.00" shape="2361.871470,36516.550926 2331.432024,36523.467499 2286.470367,36388.908321 2364.894089,36363.477215 2399.177294,36351.905073 2405.685092,36370.688114 2481.015712,36341.953538 2569.178765,36487.306552 2520.507827,36520.255117 2523.207766,36546.416643 2527.532493,36580.478321 2518.187853,36610.014887 2499.916052,36636.434783 2474.120974,36653.614597 2442.948679,36660.576528 2413.121689,36657.507941 2396.997487,36642.870529 2379.427315,36616.414376 2367.958419,36589.183688 2362.613329,36550.574642 2367.717304,36528.904243 2372.399070,36519.531865 2361.871470,36516.550926"/>
    <poly id="1128435241" type="tourism" color="207,245,201" fill="1" layer="-2.00" shape="2105.817387,36275.699408 2090.307183,36235.249117 2073.009512,36240.393810 2061.685961,36202.515043 2044.945935,36155.857490 2064.963680,36135.743081 2072.773227,36108.489147 2051.438661,36108.350279 2038.864131,36092.754963 2038.898426,36065.813813 2050.740321,36041.375144 2076.182523,36034.422720 2096.324431,36043.186233 2106.817845,36061.486067 2110.415337,36069.437988 2177.257404,36074.775400 2197.310613,36074.396497 2248.114631,36061.720925 2254.603154,36081.112712 2257.038395,36143.934014 2230.316376,36145.398380 2232.411018,36185.075749 2163.824510,36191.429716 2171.913974,36268.840470 2105.817387,36275.699408"/>
    <poly id="1128437590" type="water" color="181,209,209" fill="0" layer="-4.00" shape="4218.553932,34374.367271 4155.348543,34386.160418 4116.078552,34364.575395 4100.794071,34377.141523 4085.309170,34418.220738 4046.248255,34466.378853 4017.474064,34471.407674 4009.826159,34542.359158 3961.070159,34560.670551 3912.927786,34569.152140 3886.782429,34602.091846 3878.194679,34641.809356 3859.123965,34668.738067 3814.784200,34672.133087 3769.933103,34660.099442 3744.051738,34641.049659 3713.719713,34640.658041 3693.914409,34660.504278 3666.061154,34660.219254 3653.741784,34636.442548 3654.927124,34610.639601 3649.924450,34595.915730 3618.473880,34563.183688 3605.222577,34538.036090 3580.475391,34524.231175 3538.910467,34495.512206 3522.031460,34456.678958 3506.722519,34430.217771 3466.857079,34429.389011 3396.799978,34462.260434 3338.510845,34485.825472 3286.829480,34496.196681 3267.689090,34500.081366 3266.614845,34512.015178 3234.365142,34519.674648 3216.223277,34521.653879 3188.980780,34546.383721 3172.998065,34560.767211 3153.366219,34561.066648 3108.495308,34555.997063 3068.619293,34548.882351 3045.126515,34532.142916 3016.326820,34528.163748 2990.225100,34519.686100 2956.974551,34527.790615 2947.532091,34543.801150 2915.247122,34542.927427 2874.108031,34540.021473 2848.695106,34541.637441 2830.315216,34513.654770 2828.175636,34488.909059 2811.289491,34470.686332 2787.671605,34459.415392 2739.913317,34457.052629 2705.569326,34436.381164 2661.801596,34401.082501 2634.479168,34374.001221 2582.558360,34359.747463 2578.416297,34335.835452 2558.433514,34330.535517 2536.756264,34313.085243 2522.308063,34295.522646 2499.585953,34288.832964"/>
    <poly id="1128437591" type="water" color="181,209,209" fill="0" layer="-4.00" shape="2855.113516,35926.489019 2847.179367,35847.483831 2821.119983,35796.956646 2781.176898,35773.383738 2758.524847,35758.237140 2759.343497,35736.231258 2772.936786,35702.735950 2758.927204,35657.567184 2740.987609,35626.805599 2729.567180,35580.093793 2735.214162,35549.578757 2714.311402,35531.064296 2703.672358,35500.157155 2716.287734,35480.200460 2751.805155,35482.252449 2768.003128,35455.880796 2788.387321,35425.771724 2815.778576,35404.671395 2830.452345,35374.660889 2869.397069,35364.022519 2880.580670,35357.859968"/>
    <poly id="1128437592" type="water" color="181,209,209" fill="0" layer="-4.00" shape="4240.216535,35439.663458 4189.161507,35427.616770 4150.310014,35395.283344 4126.542872,35354.911268 4117.280321,35324.222302 4080.131686,35297.686175 4051.255411,35265.325327 4022.399412,35245.195323 3985.317137,35258.605957 3942.654359,35288.130857 3919.771687,35289.176390 3906.928322,35266.485083 3901.764521,35235.457318 3923.936819,35198.650234 3914.956387,35157.877400 3896.668085,35115.205292 3857.953427,35116.000728 3847.266614,35129.289938 3853.360129,35172.712979 3802.082170,35213.033552 3775.164543,35258.803313 3745.923911,35274.160461 3720.120442,35300.724382 3690.031777,35290.813397 3647.812061,35288.848115 3601.905672,35305.196695 3558.203948,35312.288299 3507.280236,35323.377004 3451.432673,35359.887829 3401.893020,35407.301754 3346.105333,35436.241916 3315.517778,35436.515633 3256.864630,35402.248079 3194.557120,35374.915986 3144.253886,35368.272853 3124.207128,35354.947571 3085.498486,35352.900255 3051.800214,35339.974975 3002.737913,35322.493956 2953.863584,35294.375808 2933.666197,35253.921815 2928.012998,35227.621498 2942.011822,35207.164504 2906.505839,35176.377901 2863.066923,35156.507782 2816.726627,35148.840470 2784.142606,35147.513736 2761.501754,35151.106304 2726.819604,35125.166720 2700.588041,35130.536637 2675.432713,35107.701841 2644.653483,35099.155483 2624.369143,35068.586318 2620.957568,35037.102055 2605.261072,34984.575769 2571.428558,34954.716734 2527.445722,34943.238506 2506.106563,34929.661697 2482.000241,34887.134265 2464.807049,34847.074035 2455.557248,34825.595091 2430.123332,34815.058420 2421.367723,34792.759544 2405.376086,34778.221513 2380.012097,34766.411906 2359.929769,34751.294527 2359.890650,34723.390584 2377.315441,34695.732420 2400.016593,34673.366813 2410.056311,34633.380238 2414.451156,34595.739135 2413.611788,34541.570763 2436.209511,34518.961888"/>
    <poly id="1128438265" type="amenity" color="237,199,199" fill="1" layer="-1.00" shape="2419.559764,35989.226957 2436.471267,36034.113600 2529.242739,36009.997286 2541.461011,35964.284402 2419.559764,35989.226957"/>
    <poly id="1130874638" type="building" color="255,230,230" fill="1" layer="-1.00" shape="6553.862593,34734.212525 6612.430582,34728.800358 6608.830452,34690.309204 6550.262321,34695.721383 6553.862593,34734.212525"/>
    <poly id="1130874639" type="building" color="255,230,230" fill="1" layer="-1.00" shape="6563.031100,34725.974742 6575.267280,34724.904794 6574.342914,34714.568119 6589.604583,34713.227980 6590.402896,34722.159133 6601.668437,34721.168146 6599.872158,34701.014940 6561.108744,34704.427087 6563.031100,34725.974742"/>
    <poly id="1130874640" type="building" color="255,230,230" fill="1" layer="-1.00" shape="6628.140401,34723.308859 6647.407700,34721.077269 6647.752869,34723.987791 6665.109948,34721.969394 6664.806656,34719.435141 6684.084275,34717.192512 6677.556831,34661.682238 6621.654655,34668.185944 6628.140401,34723.308859"/>
    <poly id="1130874641" type="building" color="255,230,230" fill="1" layer="-1.00" shape="6632.597377,34686.012073 6648.602075,34684.294542 6648.916213,34687.171904 6654.254554,34686.599392 6653.741425,34681.873874 6670.943891,34680.021744 6669.959399,34670.869495 6631.403524,34675.000616 6632.597377,34686.012073"/>
    <poly id="1130874642" type="building" color="255,230,230" fill="1" layer="-1.00" shape="6634.286765,34717.532888 6647.255474,34715.985945 6645.896032,34704.731227 6662.612876,34702.735926 6663.689951,34711.644527 6674.449037,34710.366569 6671.981114,34689.904442 6631.526136,34694.746802 6634.286765,34717.532888"/>
    <poly id="1130874643" type="building" color="255,230,230" fill="1" layer="-1.00" shape="6647.486757,34821.878835 6686.702719,34817.414701 6685.681985,34804.742691 6668.738563,34807.081435 6668.062830,34804.104997 6662.858931,34804.776920 6663.421564,34808.085586 6645.578687,34809.761589 6647.486757,34821.878835"/>
    <poly id="1148052506" type="building" color="255,230,230" fill="1" layer="-1.00" shape="6568.297086,34841.910337 6560.236755,34783.679535 6615.703128,34776.091540 6623.763258,34834.322367 6568.297086,34841.910337"/>
    <poly id="1150124893" type="building" color="255,230,230" fill="1" layer="-1.00" shape="3424.235457,33405.139291 3391.720366,33409.954224 3388.262409,33386.893153 3420.777527,33382.067145 3424.235457,33405.139291"/>
    <poly id="1150124915" type="building" color="255,230,230" fill="1" layer="-1.00" shape="3201.360175,35547.718808 3223.043056,35539.800673 3217.917843,35525.951554 3196.245252,35533.858610 3201.360175,35547.718808"/>
    <poly id="1156775461" type="residential" color="235,235,227" fill="1" layer="-3.00" shape="3899.062923,37037.025651 3799.140658,36945.091317 3606.854151,37012.713444 3476.575024,36880.099997 3300.461686,37027.414711 3321.908795,37069.881565 3491.184775,37085.531329 3555.471162,37175.753246 3614.489225,37313.811984 3538.025408,37397.189081 3716.515224,37600.560940 3350.990671,38447.779920 3242.310958,38435.569487 3221.288997,38639.269123 3171.553886,38722.591176 3102.057949,38710.314224 3023.600655,38662.633359 3044.268464,38249.946542 2899.792293,38143.927116 2734.012585,38078.690045 2699.962084,37961.853529 2657.155922,37933.592850 2596.361030,37804.406640 2637.166669,37710.461562 2749.370717,37697.867926 2849.004205,37623.312505 2847.113975,37557.778270 2734.917139,37580.997098 2647.495675,37506.768986 2508.730678,37611.512514 2448.077456,37563.791989 2435.401582,37443.376307 2333.803297,37416.991619 2264.282874,37388.768386 2267.624500,37264.782366 2037.849735,37282.902872 2028.646281,37119.977622 2151.513522,37086.097773 2224.686231,37163.901602 2283.464815,37154.942009 2258.366632,37069.968308 2114.002042,37029.493319 1949.894134,36914.651633 1891.026147,36868.712065 1837.355479,36744.817832 1838.913948,36624.365890 1804.799373,36477.413669 1807.980749,36266.627547 1793.094027,36097.470136 1759.205206,36098.804369 1744.025818,35916.664032 1728.874825,35869.992863 1694.577661,35623.833024 1551.648344,35404.446853 1467.807753,35349.688422 1451.293675,35089.317743 1479.411572,34873.151134 1459.357027,34625.172853 1505.510762,34529.433376 1394.723755,34357.795498 1394.496510,34233.794030 1445.770060,34017.574092 1564.999743,33935.858156 1864.273625,33892.801258 1953.100977,33742.063863 2193.638548,33736.309460 2232.637511,33626.406137 2364.476820,33610.233314 2419.845490,33686.309569 2469.852245,33749.998627 2493.426832,33982.032741 2565.000741,34153.747022 2606.042976,34189.105549 2645.198940,34167.774019 2652.192467,34086.274586 2650.256692,34001.237791 2610.990449,33965.876034 2596.591920,33882.643184 2630.396726,33854.237120 2665.699727,33661.072188 2615.637528,33565.493951 2489.041349,33521.431108 2453.118787,33356.727118 2404.891260,33289.493023 2376.146249,33160.218231 2359.858608,33020.284509 2297.398473,32965.472795 2316.844698,32876.856237 2546.827038,32940.227387 2637.840329,33016.252781 2750.003440,32961.134129 2823.029521,32939.744007 2894.342840,32960.882768 2862.533937,33116.839330 2937.478371,33171.631590 2900.297978,33315.200590 2912.823618,33343.525542 3000.134738,33341.603230 3001.688515,33206.950959 3081.817729,33178.465818 3113.793498,33118.175348 3051.243458,33015.533423 3106.376899,32949.890047 3218.739731,33009.932104 3282.949884,33045.252607 3263.644235,33218.907757 3318.986900,33275.506387 3361.715354,33257.712531 3400.610070,33075.169213 3159.723957,32884.238877 3148.856021,32786.820701 3041.835401,32723.216881 2820.835464,32705.890420 2694.429313,32768.117344 2612.420699,32750.540186 2546.365897,32678.024049 2492.589840,32499.172635 2588.806824,32490.148525 2662.013806,32576.831181 2760.025473,32578.430816 2861.452643,32494.985085 3007.702645,32563.832733 3230.641940,32675.064453 3458.788318,32710.105286 3572.905287,32750.655064 3687.078459,32824.876225 3884.987570,32895.415824 3974.161932,32937.781227 3953.011477,33081.320856 3885.346513,33109.780690 3759.106474,33271.217778 3823.400594,33357.920746 3740.088289,33618.482869 3627.872577,33641.706011 3652.988188,33744.413413 3670.993598,33850.674822 3807.994853,33735.297379 3875.517476,33623.568304 4053.691055,33614.415890 4076.962735,33678.154453 4217.714752,33667.284102 4208.046969,34290.894149 4102.999624,34337.124836 3918.004646,34523.441341 3948.425133,34601.335631 4012.556329,34594.144642 4092.949758,34721.554405 4137.588206,34779.944667 4232.078760,34815.207669 4256.873399,35801.845540 4232.224981,35977.246556 3925.677696,36978.527547 3899.062923,37037.025651"/>
    <poly id="1156787782" type="leisure" color="207,245,201" fill="1" layer="-2.00" shape="1779.424675,34306.555788 1871.206906,34341.577250 1921.316405,34313.029563 1910.794571,34279.687656 1918.174924,34277.538128 1888.773916,34186.706570 1873.672447,34173.883105 1836.443203,34180.679970 1813.343296,34170.925939 1765.517322,34274.448715 1779.424675,34306.555788"/>
    <poly id="1156787783" type="leisure" color="207,245,201" fill="1" layer="-2.00" shape="1824.166588,34210.919481 1809.010529,34219.347940 1797.301391,34232.098017 1790.214159,34247.861483 1788.489526,34265.043111 1792.289555,34281.893763 1801.228988,34296.687432 1814.406642,34307.942558 1830.477840,34314.499374 1848.986743,34315.561768 1866.782137,34310.393833 1881.809921,34299.585905 1892.316653,34284.380820 1897.076562,34266.562826 1895.545976,34248.191661 1887.914598,34231.392163 1875.043111,34218.110866 1858.442154,34209.905735 1841.221941,34207.656659 1824.166588,34210.919481"/>
    <poly id="1156787783#1" type="sport" color="79,230,125" fill="1" layer="-2.00" shape="1824.166588,34210.919481 1809.010529,34219.347940 1797.301391,34232.098017 1790.214159,34247.861483 1788.489526,34265.043111 1792.289555,34281.893763 1801.228988,34296.687432 1814.406642,34307.942558 1830.477840,34314.499374 1848.986743,34315.561768 1866.782137,34310.393833 1881.809921,34299.585905 1892.316653,34284.380820 1897.076562,34266.562826 1895.545976,34248.191661 1887.914598,34231.392163 1875.043111,34218.110866 1858.442154,34209.905735 1841.221941,34207.656659 1824.166588,34210.919481"/>
    <poly id="1156787804" type="water" color="181,209,209" fill="0" layer="-4.00" shape="3472.572168,36324.449936 3456.803300,36324.034053 3425.998950,36280.963160 3389.643350,36234.459462 3361.893804,36232.824455 3326.220327,36223.023339 3285.546399,36217.802224 3261.190609,36190.028518 3225.882533,36170.619421 3171.450172,36169.318408 3123.839047,36135.497221 3093.211369,36129.694771 3052.099429,36122.172732 3016.404261,36117.995216 2980.257053,36138.988651 2939.964932,36163.542402 2912.426960,36158.974624 2890.938779,36141.711705 2895.861344,36104.302205 2921.668875,36040.026022 2908.504359,36005.348717 2871.356574,35967.713554 2854.100722,35949.745994"/>
    <poly id="1156787805" type="water" color="181,209,209" fill="0" layer="-4.00" shape="2854.100722,35949.745994 2855.113516,35926.489019"/>
    <poly id="1157001187" type="residential" color="235,235,227" fill="1" layer="-3.00" shape="4429.769289,36052.253964 4422.009263,36074.415034 4413.622353,36098.403462 4451.564686,36112.962808 4483.110921,36099.872228 4520.922258,36103.839279 4556.185411,36197.754248 4593.978953,36190.973863 4626.500992,36263.409258 4760.135496,36245.747827 4819.742195,36369.143947 5070.973461,36430.491317 5166.839056,36428.998712 5232.680497,36235.591313 5137.992342,36121.635890 5090.631642,36054.591505 5108.156810,36042.476529 5140.614609,36075.995773 5164.909988,36067.899024 5182.323492,35979.266935 5360.364315,35863.538314 5289.905102,35706.586370 5202.180006,35732.227996 5195.509866,35784.593184 5007.930092,35843.966485 4943.043140,35795.745214 4899.884520,35825.345827 4925.661016,35903.160960 4886.511707,35908.592357 4779.784402,35868.497266 4783.791077,35842.988671 4862.029784,35801.244115 4842.999891,35719.389207 4730.900871,35698.086568 4648.590523,35731.780439 4617.712008,35844.597871 4555.628117,35856.775080 4358.537206,35882.611590 4327.513748,35943.661907 4445.299571,36007.832204 4429.769289,36052.253964"/>
    <poly id="1157001188" type="residential" color="235,235,227" fill="1" layer="-3.00" shape="4290.374188,34782.901696 4295.459410,35217.303246 4391.363787,35216.093753 4430.370249,35223.346023 4470.909822,35246.103008 4325.190431,35317.380931 4343.804721,35376.987977 4487.251278,35330.651534 4554.840569,35374.837559 4559.053185,35475.521896 4626.637293,35517.029628 4661.694126,35490.120072 4658.920198,35441.799001 4703.493290,35449.773407 4746.765807,35489.981862 4766.977383,35465.786302 4765.583229,35440.275399 4860.036984,35398.515672 4966.674413,35380.888635 5017.923691,35340.527625 5131.287565,35305.446780 5163.539023,35208.733108 5101.304506,35134.993818 5128.236622,35089.314891 5172.774053,35074.467209 5220.220636,35193.877252 5306.653098,35197.768875 5305.134139,35093.051177 5375.294284,35059.380013 5384.658596,35005.671391 5491.201736,34919.577689 5535.638943,34847.019497 5512.102633,34708.732179 5301.750911,34744.085534 5160.761923,34438.927059 4984.610654,34512.162170 5014.310449,34710.574575 4934.831345,34716.734687 4909.873965,34488.208176 4807.187712,34449.445644 4673.618760,34516.793331 4650.754939,34574.553305 4621.071629,34592.056831 4640.114293,34673.922448 4567.265745,34718.337792 4465.866965,34639.296699 4427.889064,34535.989251 4399.402178,34458.168375 4284.167417,34463.726412 4290.374188,34782.901696"/>
    <poly id="1157001201" type="leisure" color="207,245,201" fill="1" layer="-2.00" shape="4545.842433,35044.166302 4541.463179,35050.128374 4539.213050,35057.160622 4539.297407,35064.543249 4541.735655,35071.512490 4546.268456,35077.360379 4552.430118,35081.489971 4559.579661,35083.470642 4566.993855,35083.093268 4574.290314,35080.181378 4580.178616,35075.013793 4583.998811,35068.189292 4585.308116,35060.494469 4583.953031,35052.792925 4580.089940,35045.992032 4574.164168,35040.865869 4566.847929,35037.999975 4558.998930,35037.736078 4551.897420,35039.883922 4545.842433,35044.166302"/>
    <poly id="1157001201#1" type="sport" color="79,230,125" fill="1" layer="-2.00" shape="4545.842433,35044.166302 4541.463179,35050.128374 4539.213050,35057.160622 4539.297407,35064.543249 4541.735655,35071.512490 4546.268456,35077.360379 4552.430118,35081.489971 4559.579661,35083.470642 4566.993855,35083.093268 4574.290314,35080.181378 4580.178616,35075.013793 4583.998811,35068.189292 4585.308116,35060.494469 4583.953031,35052.792925 4580.089940,35045.992032 4574.164168,35040.865869 4566.847929,35037.999975 4558.998930,35037.736078 4551.897420,35039.883922 4545.842433,35044.166302"/>
    <poly id="1157001203" type="residential" color="235,235,227" fill="1" layer="-3.00" shape="4278.168356,33650.968731 4922.207874,33585.466635 4988.752124,33817.634113 5111.570404,33778.498098 5293.971351,33837.280810 5275.227377,33942.041587 5192.970882,34016.010980 5149.753368,34012.050902 5130.984436,34093.977406 5048.645537,34115.593237 5051.530290,34233.734842 4969.218103,34271.455870 4920.582635,34256.768588 4879.820383,34097.070092 4788.068962,34141.514848 4727.283839,34130.876793 4709.639699,34077.200573 4652.961089,34096.087162 4650.438739,34208.869251 4551.897121,34230.514052 4497.785096,34170.190087 4450.625048,34230.679784 4407.538003,34305.928461 4286.021555,34316.876132 4278.168356,33650.968731"/>
    <poly id="1157001204" type="residential" color="235,235,227" fill="1" layer="-3.00" shape="4615.656523,33581.934016 4595.035689,33356.411806 4590.801015,33242.290456 4633.911535,33179.118204 4775.775378,33220.505871 4839.331162,33275.458301 4913.635686,33296.811576 4951.313316,33213.515181 5016.104806,33189.237375 5098.622689,33283.088666 5137.797851,33289.744740 5240.354196,33242.584209 5233.522385,33187.550990 5152.459202,33170.224890 5151.022325,33111.154140 5230.658449,33088.203924 5318.491846,33121.624489 5325.433671,33239.770635 5364.940339,33462.585172 5046.367883,33538.281118 4615.656523,33581.934016"/>
    <poly id="1157001207" type="residential" color="235,235,227" fill="1" layer="-3.00" shape="5134.682505,33725.675068 5097.382676,33560.558048 5678.613530,33415.670570 5691.025268,33460.290795 5872.821153,33420.947044 5871.624494,33375.191376 6025.334437,33325.842663 6120.684204,33285.528263 6164.701083,33439.469044 6116.614324,33561.197527 6030.187999,33560.212423 6012.200102,33542.375432 5986.430033,33574.790765 5931.440459,33586.032806 5896.483124,33481.178837 5846.013672,33510.267801 5732.769929,33591.919724 5760.996064,33697.901757 5729.707415,33787.229727 5648.948025,33829.759578 5608.519395,33813.087143 5562.519614,33826.552256 5533.227993,33759.633276 5542.164350,33735.069107 5506.186074,33698.300452 5446.630490,33655.979392 5353.506382,33684.030386 5279.454371,33703.119300 5279.507509,33736.601705 5209.923908,33746.751503 5200.906344,33719.979863 5134.682505,33725.675068"/>
    <poly id="1157003111" type="water" color="181,209,209" fill="1" layer="-4.00" shape="2075.064222,34827.356365 1937.703278,34845.390144 1925.559730,34846.087179 1919.135077,34839.723208 1912.605880,34775.293377 1914.950804,34769.909800 1954.434963,34760.109444 1963.217329,34762.440209 1972.710772,34786.929104 1979.131210,34790.946553 2060.120550,34775.360552 2067.220149,34778.026447 2078.430991,34821.638924 2075.064222,34827.356365"/>
    <poly id="1157003112" type="water" color="181,209,209" fill="1" layer="-4.00" shape="1587.524375,34746.926407 1585.830944,34707.359118 1621.886820,34658.038082 1672.720285,34699.132107 1673.614564,34742.331365 1637.558724,34791.652288 1632.285199,34793.687435 1624.966184,34789.660691 1587.524375,34746.926407"/>
    <poly id="1157003117" type="water" color="181,209,209" fill="1" layer="-4.00" shape="3639.585616,35669.711332 3653.946917,35698.421200 3657.906888,35719.621997 3644.744839,35734.431947 3628.482878,35741.986134 3600.710992,35745.940395 3593.697818,35745.111065 3587.512596,35739.266244 3584.972655,35733.415245 3571.984361,35680.152888 3575.900912,35675.685587 3583.750955,35670.647117 3630.038621,35666.661478 3639.585616,35669.711332"/>
    <poly id="1157006054" type="water" color="181,209,209" fill="0" layer="-4.00" shape="2433.463205,34490.188316 2413.852720,34467.576577 2382.208188,34443.558310 2365.267531,34429.863215 2359.130074,34404.892203 2374.179097,34376.784446 2400.240881,34344.849611 2420.088462,34320.386058 2427.119501,34301.711931 2461.785797,34288.124842 2499.585953,34288.832964 2527.431600,34278.534356 2547.595271,34251.602109 2554.390106,34215.971332 2574.472770,34178.136674 2613.368943,34102.956691 2631.974590,34064.870129 2608.362099,34039.442681 2578.010993,34040.636068 2534.840567,34052.079480 2512.742602,34053.988994 2502.873724,34038.919857 2478.003657,34003.289550 2465.016799,33953.713985 2469.819571,33912.939790 2459.222293,33900.705532 2471.485190,33861.866251 2476.693215,33810.753260 2509.532396,33773.604437 2537.287647,33717.293791 2514.513652,33675.749105 2490.015133,33640.273093 2452.063112,33595.368267 2430.609307,33541.335975 2399.204694,33525.519094 2366.013207,33521.338552 2335.328399,33497.971727 2288.756140,33461.428306 2254.953160,33444.520174 2234.389612,33415.346669 2231.075066,33398.373313 2234.245004,33380.502932 2225.702823,33356.842366 2223.014893,33332.164142 2230.799207,33312.979454 2232.881306,33299.007162 2229.435118,33289.328257 2217.620013,33277.937542 2154.380071,33237.306663"/>
    <poly id="1157006055" type="water" color="181,209,209" fill="0" layer="-4.00" shape="2436.209511,34518.961888 2433.463205,34490.188316"/>
    <poly id="1157012573" type="water" color="181,209,209" fill="0" layer="-4.00" shape="2887.658113,35348.018713 2882.044514,35326.699224 2859.119743,35291.640490 2829.747372,35254.578534 2824.781833,35225.941573 2813.339390,35208.074615 2787.435590,35194.084784 2770.935487,35171.810301 2761.501754,35151.106304"/>
    <poly id="1157012574" type="water" color="181,209,209" fill="0" layer="-4.00" shape="2880.580670,35357.859968 2887.658113,35348.018713"/>
    <poly id="1157012576" type="landuse" color="194,194,130" fill="1" layer="-3.00" shape="2653.588792,35424.369436 2630.716030,35372.088138 2644.475733,35321.579952 2717.931716,35292.517836 2727.879380,35317.759050 2803.323325,35344.856092 2816.583168,35356.776020 2776.325424,35390.196059 2741.973276,35458.184289 2701.694511,35479.362654 2653.588792,35424.369436"/>
    <poly id="1157016962" type="water" color="181,209,209" fill="1" layer="-4.00" shape="2707.044512,36423.320142 2734.116017,36397.582423 2750.725129,36388.399600 2758.916450,36389.912751 2776.614958,36419.125182 2774.585059,36427.529831 2769.739222,36437.710383 2735.247787,36460.151498 2722.716778,36462.973796 2717.843816,36457.636171 2707.044512,36423.320142"/>
    <poly id="1157016979" type="water" color="181,209,209" fill="1" layer="-4.00" shape="2164.292899,36118.320462 2165.847086,36132.817615 2156.400872,36139.951624 2095.276422,36149.989489 2088.606689,36139.065604 2088.328020,36127.610052 2089.333029,36117.945323 2090.099777,36113.627178 2094.947239,36110.308975 2132.042230,36111.770096 2150.974071,36113.772897 2164.292899,36118.320462"/>
    <poly id="1157070107" type="water" color="181,209,209" fill="0" layer="-4.00" shape="419.296577,43712.198805 403.198602,43703.175193 380.909183,43700.328686 352.827540,43707.322308 334.606208,43705.231856 315.401072,43696.026092 291.902234,43670.634962 287.419101,43652.535041 285.620298,43624.025361 290.441926,43613.998925 332.007504,43560.357869 335.468579,43551.297025 337.005086,43539.738315 361.165377,43511.367310 378.173299,43483.209202 393.390289,43435.971995 392.007295,43425.182593 394.102439,43403.417438 394.279102,43393.200643 390.581454,43386.466812 382.820016,43381.279276 372.744641,43380.523653 360.541508,43384.398830 347.362641,43385.386932 318.471032,43373.886264 301.001008,43360.050465 293.624391,43351.010312 284.472469,43331.181521 279.996597,43316.933519 277.833490,43303.057437 282.467585,43292.068380 301.976428,43260.053496 311.639811,43245.003684 361.953244,43209.841930 376.840254,43195.169614 380.706558,43187.458401 382.786238,43162.981436 385.868157,43149.881237 384.095896,43135.240656 389.674259,43115.959344 415.575359,43079.881283 444.405933,43059.017229 458.155427,43053.988035 477.734826,43053.364218 489.165125,43055.467727 498.679850,43065.278725 512.290570,43090.489660 518.942808,43120.340531 518.389168,43138.649289 522.480870,43146.345382 532.371574,43153.067508 558.363010,43164.574058 571.936376,43170.138088 582.426690,43182.836233 587.091636,43188.029722 597.553399,43191.098121 606.666386,43190.494252 656.649629,43182.308611 662.836871,43179.219827 669.011538,43163.988653 677.530047,43160.120666 707.362977,43156.201454 751.913151,43145.912221 771.091894,43140.862022 812.123371,43114.585238 824.130332,43110.511546 831.300364,43108.572135 836.130449,43102.785191 838.055421,43094.502160 833.773004,43084.105572 827.174672,43077.177845 818.246137,43071.604881 812.993449,43061.210118 813.547250,43048.302923 812.379281,43041.951656 805.584080,43034.636902 798.772246,43018.467187 800.300261,43007.672293 805.517527,42999.183841 809.765271,42991.084616 812.067811,42980.487507 807.961933,42959.685976 809.278659,42940.800229 807.107512,42916.917958 804.760277,42909.207450 803.791299,42904.394366 807.254248,42896.108447 807.239414,42888.205393 802.547520,42863.165637 800.189630,42844.286789 799.783306,42836.782945 801.508186,42826.375090 806.532285,42819.425558 832.273392,42801.844379 843.898331,42797.583255 859.401616,42797.366032 872.574638,42798.492505 899.113798,42793.627924 905.515238,42794.578928 908.039934,42797.850553 907.475236,42804.979878 900.908684,42820.599086 901.887234,42825.024751 905.382543,42828.482728 911.597581,42834.636391 919.562076,42843.487558 928.279939,42846.747607 943.787497,42848.843825 954.822983,42843.997241 975.148769,42828.352370 980.366561,42820.063216 983.249772,42810.804370 985.543017,42789.614524 988.047194,42781.894941 993.641163,42770.516912 1003.122328,42762.407984 1023.648438,42754.477716 1057.724055,42739.183681 1098.370489,42710.406855 1134.558634,42682.014748 1153.323319,42664.834458 1162.011878,42646.698823 1164.084294,42617.606343 1161.941150,42608.556091 1157.862802,42602.398368 1145.448097,42598.370239 1136.517992,42592.033356 1130.661926,42567.958657 1127.699568,42540.214837 1130.791170,42531.929684 1134.631231,42515.352661 1131.699943,42498.788206 1127.019589,42485.304107 1128.364592,42475.859980 1132.993149,42466.996401 1145.185718,42456.945504 1148.633173,42434.591335 1149.773490,42420.520860 1151.110347,42412.238968 1154.393844,42407.218742 1165.426871,42400.844831 1184.980369,42391.366965 1206.672731,42383.036311 1233.798928,42377.020071 1244.838761,42374.298886 1252.186427,42367.732614 1276.716804,42325.493289 1281.929568,42314.304244 1283.641667,42296.768214 1290.373293,42269.593123 1291.512688,42254.947090 1286.037239,42230.096830 1286.208476,42216.614801 1297.383748,42180.941798 1321.541858,42143.717377 1330.034778,42125.582213 1335.215358,42096.871454 1337.860203,42058.900845 1342.277602,42041.747248 1351.168198,42026.511371 1371.302852,42012.793354 1376.701962,42001.803242 1375.905083,41989.474147 1369.294827,41976.181704 1368.699040,41966.553010 1374.078650,41944.959094 1375.221695,41932.239025 1364.111661,41897.005584 1366.611565,41886.784549 1395.804169,41847.613970 1407.400514,41832.948729 1415.493726,41804.996397 1417.215250,41792.474507 1414.474542,41778.411197 1403.780411,41761.661736 1395.995137,41743.755787 1378.304453,41711.423380 1370.919154,41703.345733 1354.586318,41674.087959 1328.776365,41655.628600 1320.808715,41639.660050 1313.169647,41600.358033 1312.554264,41580.125545 1322.212208,41561.036333 1323.533587,41544.264785 1328.945293,41534.436856 1330.850474,41515.162703 1337.420820,41506.671957 1343.208805,41493.755168 1342.975750,41473.710145 1339.274551,41459.460451 1337.899148,41452.522897 1342.345499,41445.386452 1354.733727,41434.571638 1362.071593,41422.415745 1363.987830,41409.118686 1361.444921,41396.018004 1355.804407,41388.136390 1351.150577,41383.518234 1350.748361,41378.117440 1354.028248,41370.983146 1354.607444,41365.979019 1349.945058,41362.323857 1343.734230,41358.671549 1332.279049,41343.661330 1308.777015,41317.504992 1300.622952,41312.505900 1289.566354,41306.549188 1280.639513,41296.747709 1269.966277,41291.565114 1250.195281,41290.251246 1239.723506,41287.957235 1210.238175,41269.704097 1202.077645,41261.240558 1195.472314,41250.848188 1190.205374,41232.937683 1189.218248,41223.885299 1190.351922,41206.151113 1187.422281,41196.139347 1178.681478,41186.525748 1164.702569,41174.597428 1129.594350,41147.101411 1114.031716,41127.339421 1109.262012,41104.867709 1113.289098,41088.755250 1114.270872,41072.648444 1111.870759,41053.194094 1103.721621,41028.714151 1081.060945,41000.243226 1061.769634,40968.412246 1041.749165,40905.368868 1033.923663,40871.834152 1027.815166,40856.747793 1027.771449,40833.260060 1053.018629,40797.992439 1108.292710,40760.643524 1135.249000,40739.452271 1154.413628,40702.856787 1158.427428,40685.061929 1159.072717,40665.601938 1153.979690,40652.528158 1143.498453,40639.796428 1117.810307,40615.692141 1096.179433,40597.269678 1062.737275,40578.216142 1047.538375,40571.193632 1034.037796,40572.558060 1001.323398,40584.030806 964.227514,40593.154156 930.853470,40610.671798 908.244879,40616.082355 878.552837,40615.130614 856.272017,40608.121536 849.156591,40595.726829 845.058276,40568.217681 837.579156,40538.036238 840.576549,40517.896635 846.961050,40503.794207 872.927726,40494.359340 908.004129,40487.242989 928.226893,40470.092986 947.756451,40446.568726 946.366517,40426.448403 935.171665,40396.605916 931.730703,40361.712696 915.482857,40334.901416 897.911090,40317.833092 869.862667,40301.780567 850.966017,40299.458296 831.403117,40305.206384 815.879519,40306.906847 788.196468,40298.568672 764.221485,40291.241906 749.371046,40288.580097 725.418086,40292.986182 719.360402,40299.705210 711.271509,40307.778444 699.810169,40312.161078 678.203671,40307.165483 648.848352,40309.910482 618.126072,40304.932153 603.944776,40301.273034 593.466666,40290.556165 581.287226,40275.481444 573.848672,40267.105414 560.001023,40259.748754 550.540289,40252.051749 546.785693,40231.924861 546.745083,40210.451637 550.081601,40189.647217 546.664493,40167.837249 551.366761,40154.081017 593.817143,40120.783607 607.964407,40106.323303 615.004931,40078.804274 636.172389,40031.456687 657.397489,40014.636522 684.690117,39990.765266 714.026490,39977.626862 752.785266,39951.708597 775.653987,39908.387026 788.788000,39892.932610 813.387477,39875.099081 868.700682,39857.219179 881.845485,39847.465206 929.724349,39828.913163 941.179533,39815.476516 951.241296,39785.594384 961.003378,39772.149842 982.916822,39758.693730 1000.105029,39746.917821 1036.200861,39737.453321 1053.721987,39727.016165 1062.467462,39710.894952 1082.691397,39693.745175 1108.260331,39652.765666 1107.880437,39631.636222 1105.152239,39613.521823 1112.205297,39597.735842 1125.673738,39578.584154 1143.494142,39545.666021 1172.476740,39524.814264 1187.960167,39500.965774 1194.680509,39483.841137 1192.631525,39470.086537 1188.561084,39463.043306 1180.113823,39456.351305 1177.393752,39442.597949 1180.055449,39424.805628 1185.099418,39416.749353 1210.716595,39395.892830 1236.958673,39355.587499 1251.114651,39345.156789 1256.829542,39331.387854 1258.158489,39318.634265 1250.355004,39297.175400 1244.590549,39284.102846 1242.488921,39241.824315 1247.524930,39229.407012 1268.406516,39204.530331 1271.089219,39192.449439 1260.209677,39154.559237 1262.886174,39139.113473 1257.797509,39123.017915 1260.124226,39108.247987 1260.764159,39085.766293 1265.455179,39070.992004 1273.873350,39056.221912 1273.169646,39044.136199 1259.921165,38998.192365 1251.125963,38982.103650 1248.713360,38955.941719 1253.385209,38930.762896 1277.983426,38905.547322 1307.655157,38893.748762 1339.718869,38891.343173 1394.695373,38873.454736 1414.913511,38857.987870 1424.353706,38854.273607 1436.848909,38855.601069 1451.027602,38857.246448 1485.766574,38849.800001 1505.324160,38840.034835 1515.087325,38826.601730 1523.841124,38814.498719 1557.203098,38787.928260 1600.037840,38769.730662 1607.775127,38760.662372 1612.823720,38749.241357 1612.103159,38727.769423 1603.988455,38716.715530 1590.455643,38701.299393 1581.641106,38680.174286 1580.946738,38667.424430 1584.634247,38651.312768 1585.902399,38610.710525 1591.605622,38590.234129 1593.945503,38576.803550 1588.789678,38523.793966 1590.781522,38506.346091 1603.194465,38468.070096 1607.216717,38454.304394 1605.501349,38436.520151 1599.726495,38417.747127 1586.531099,38400.659009 1564.897788,38382.235922 1539.566386,38368.523808 1520.277163,38339.038888 1507.056434,38308.181444 1504.006796,38300.472152 1496.565476,38296.456765 1475.986672,38295.830306 1447.282003,38289.507324 1427.338123,38274.778267 1421.587456,38263.709065 1419.835690,38231.834480 1412.348632,38197.291797 1412.642568,38171.789021 1413.291519,38159.700833 1409.567614,38150.321426 1394.012885,38136.248477 1373.714937,38108.769019 1357.828075,38099.411973 1342.307656,38098.433259 1293.043428,38107.910176 1275.164777,38110.300751 1259.295593,38104.961702 1244.401907,38085.519370 1233.899255,38062.051016 1221.263171,37979.192077 1224.258480,37957.370182 1231.660587,37945.612648 1230.630761,37935.885182 1221.795504,37904.023702 1221.100821,37891.273868 1237.850818,37825.472870 1261.409370,37789.854686 1265.427814,37774.085483 1259.603214,37723.080698 1260.252092,37711.003577 1270.355254,37696.894528 1275.384349,37680.437209 1273.645036,37649.901942 1261.126621,37636.509786 1256.719155,37626.113360 1254.328026,37611.684219 1264.075041,37589.185771 1271.487861,37583.128610 1290.056638,37585.108895 1306.257797,37585.411122 1331.890491,37571.273535 1350.112981,37570.232780 1361.260425,37579.277536 1369.709673,37580.933382 1378.807427,37575.880427 1437.506346,37558.328519 1460.096260,37545.868088 1504.659053,37550.490734 1542.133150,37557.805065 1593.147708,37584.221460 1604.309583,37595.601848 1608.729068,37612.717029 1620.587116,37637.854518 1620.272664,37652.288637 1607.825393,37672.113163 1586.925902,37688.588232 1580.531637,37698.340322 1578.189768,37710.752574 1580.566518,37717.466924 1589.685063,37723.825852 1602.855312,37726.812525 1631.198819,37721.392594 1645.708888,37717.348258 1660.905347,37721.681670 1671.381341,37730.716795 1692.380215,37768.931962 1699.476159,37775.969816 1719.410057,37784.998866 1739.668839,37790.994536 1778.475414,37787.570392 1814.244555,37783.144590 1829.416027,37773.719851 1863.105111,37738.095340 1869.823287,37724.656913 1870.474463,37707.875635 1864.028505,37689.092673 1845.760647,37664.962767 1835.573268,37632.771351 1833.855039,37619.016102 1835.860628,37603.239624 1855.340567,37549.510320 1856.321552,37532.396388 1852.909988,37512.943834 1846.129253,37497.515293 1820.751783,37464.676154 1812.968824,37448.917380 1810.909216,37434.830693 1812.582555,37423.747931 1820.997252,37411.988858 1819.618530,37397.568880 1815.196194,37378.782283 1802.006864,37359.679488 1790.500560,37346.274020 1750.956654,37313.792703 1739.444814,37297.376606 1721.818866,37257.472832 1715.385953,37246.072712 1693.080693,37227.993802 1686.638600,37211.557467 1686.608741,37195.120554 1691.292776,37170.273963 1691.589062,37151.478833 1720.178182,37093.039736 1733.973250,37070.191130 1748.475416,37061.442731 1795.019585,37047.600089 1819.645902,37035.811695 1827.384156,37026.732472 1845.878350,36987.106454 1846.542878,36977.707961 1838.075163,36965.979409 1824.228871,36960.625064 1802.282313,36952.617835 1778.287560,36936.888420 1752.238488,36904.382673 1727.235935,36891.001717 1711.681496,36877.603651 1701.191566,36861.185730 1678.480368,36807.532904 1664.600345,36783.727302 1635.185204,36757.271354 1612.537184,36738.517993 1600.009781,36720.421413 1594.234910,36701.969409 1595.534434,36672.778987 1597.874022,36659.016382 1607.627008,36639.196787 1634.244184,36614.642328 1660.849215,36577.679972 1703.644452,36540.024152 1710.718362,36528.931590 1721.781701,36491.322364 1729.515303,36473.864138 1724.760367,36459.771293 1718.675212,36452.399537 1720.011512,36443.342953 1741.856022,36394.634471 1744.534118,36379.531973 1742.492554,36369.806326 1737.750380,36362.764189 1731.325032,36355.725104 1717.101508,36330.580779 1715.740227,36320.178714 1716.724208,36304.747226 1714.335145,36291.325283 1700.085945,36252.079557 1696.681250,36236.656034 1695.640021,36220.541966 1700.556775,36141.668895 1702.190015,36108.448908 1698.751766,36074.551870 1688.907520,36044.363391 1684.158534,36033.635422 1677.395314,36028.279408 1659.847687,36026.628853 1653.421566,36019.257742 1649.346824,36010.210993 1649.972853,35979.671449 1640.813706,35957.196605 1634.714894,35942.442117 1631.664255,35934.389689 1632.320839,35926.341586 1634.313081,35908.882702 1632.598738,35891.773689 1625.141623,35873.999935 1610.578567,35849.863576 1590.966448,35831.768840 1560.902066,35818.397359 1554.135039,35811.026910 1528.030043,35743.478304 1516.796919,35710.779888 1507.910393,35668.137549 1503.180089,35656.457698 1455.499377,35615.646223 1442.567151,35613.909977 1419.066848,35615.712931 1409.059910,35609.887022 1378.433555,35571.955584 1351.347799,35544.543986 1338.426260,35548.663119 1333.737673,35559.773588 1339.087886,35588.398350 1346.175359,35607.080278 1341.505024,35628.119289 1334.470170,35638.071861 1308.038621,35646.300183 1293.363130,35656.842398 1291.626970,35667.371878 1286.335837,35670.879309 1276.631338,35672.280756"/>
    <poly id="1157076116" type="water" color="181,209,209" fill="1" layer="-4.00" shape="2091.770385,36435.378767 2137.521950,36415.971057 2163.862948,36409.570591 2176.141658,36410.057826 2181.030228,36424.028807 2184.695217,36475.657524 2183.684270,36482.012734 2133.586029,36501.693731 2113.628395,36503.245829 2105.657315,36474.780449 2091.770385,36435.378767"/>
    <poly id="1157079419" type="parking" color="184,184,179" fill="1" layer="-1.00" shape="3395.095031,34074.363769 3378.370467,34084.110554 3357.436055,34053.785106 3372.807711,34044.040610 3395.095031,34074.363769"/>
    <poly id="1169526445" type="water" color="181,209,209" fill="1" layer="-4.00" shape="6368.219970,34890.527441 6412.239765,34887.350353 6411.433998,34839.513100 6362.229318,34842.354939 6368.219970,34890.527441"/>
    <poly id="1169526446" type="leisure" color="207,245,201" fill="1" layer="-2.00" shape="6578.340226,34941.324406 6568.329663,34849.824333 6625.198620,34841.116327 6635.998939,34936.090784 6578.340226,34941.324406"/>
    <poly id="1169526447" type="forest" color="140,196,107" fill="1" layer="-4.00" shape="6408.753047,34951.177174 6410.090701,34913.918245 6437.423468,34836.850454 6413.524387,34774.238420 6378.717823,34785.315554 6347.244139,34848.852845 6352.909347,34900.302142 6323.628726,34938.920743 6303.538181,34800.494246 6361.367861,34785.153741 6368.230865,34754.937116 6372.534520,34712.294350 6457.601151,34699.303676 6460.111023,34808.724008 6518.000089,34805.282726 6518.126026,34765.568417 6523.839604,34739.935997 6522.328958,34696.981063 6536.271968,34779.930207 6555.744162,34934.241343 6408.753047,34951.177174"/>
    <poly id="1169526675" type="building" color="255,230,230" fill="1" layer="-1.00" shape="6238.655834,34829.814303 6230.049412,34773.200506 6278.850125,34762.666200 6285.383013,34820.854923 6238.655834,34829.814303"/>
    <poly id="1171252973" type="building" color="255,230,230" fill="1" layer="-1.00" shape="6344.744020,34739.565326 6360.338742,34739.951160 6360.583938,34731.405831 6343.801779,34731.154626 6344.744020,34739.565326"/>
    <poly id="1171252974" type="building" color="255,230,230" fill="1" layer="-1.00" shape="6352.760964,34727.953250 6361.652436,34727.762640 6361.591938,34715.133464 6352.079983,34714.771588 6352.760964,34727.953250"/>
    <poly id="1171253443" type="building" color="255,230,230" fill="1" layer="-1.00" shape="6663.843971,34628.452755 6663.944519,34619.752691 6644.529205,34619.781832 6644.184752,34631.105519 6663.843971,34628.452755"/>
    <poly id="1171253444" type="leisure" color="207,245,201" fill="1" layer="-2.00" shape="6474.910900,34679.641803 6471.501333,34623.983002 6491.081078,34623.422108 6496.305949,34677.606047 6474.910900,34679.641803"/>
    <poly id="1171253445" type="building" color="255,230,230" fill="1" layer="-1.00" shape="6704.497706,34673.452052 6725.706319,34671.029484 6725.076024,34643.203988 6702.748529,34643.292759 6704.497706,34673.452052"/>
    <poly id="1171253446" type="building" color="255,230,230" fill="1" layer="-1.00" shape="6702.916516,34638.234160 6723.588456,34636.011629 6721.317547,34602.244756 6697.607877,34603.497804 6702.916516,34638.234160"/>
    <poly id="1171253963" type="building" color="255,230,230" fill="1" layer="-1.00" shape="6618.359334,34537.039151 6645.571350,34536.633008 6644.364817,34482.786126 6615.447426,34482.353621 6618.359334,34537.039151"/>
    <poly id="1171254998" type="college" color="237,199,199" fill="1" layer="-2.00" shape="6673.879309,35528.480696 6788.470758,35539.488478 6779.422288,35641.676263 6656.226317,35601.061886 6673.879309,35528.480696"/>
    <poly id="1171264665" type="amenity" color="237,199,199" fill="1" layer="-1.00" shape="8638.594200,32753.951723 8645.046925,32684.410196 8657.322009,32642.742366 8666.935085,32603.048405 8652.592494,32530.657628 8640.043148,32478.032837 8692.413045,32420.238462 8729.070762,32368.166065 8751.464356,32353.657772 8757.077777,32334.567920 8843.321772,32295.599674 8971.187359,32528.396933 8988.627618,32532.446565 9027.217837,32541.835900 9082.314408,32567.473863 9074.578526,32606.013902 9006.701427,32615.535878 8897.297399,32666.245227 8822.993673,32696.585602 8734.638736,32723.503230 8638.594200,32753.951723"/>
    <poly id="1171264671" type="building" color="255,230,230" fill="1" layer="-1.00" shape="8894.920834,32505.820875 8931.261478,32486.180227 8905.664297,32446.157873 8873.130030,32462.229331 8894.920834,32505.820875"/>
    <poly id="1171265304" type="leisure" color="207,245,201" fill="1" layer="-2.00" shape="8757.668086,32358.386631 8795.023990,32431.686896 8802.686213,32438.018722 8814.472863,32439.175916 8830.047914,32431.107856 8889.268871,32397.777372 8842.752536,32302.341195 8760.149143,32337.286585 8757.668086,32358.386631"/>
    <poly id="1171265305" type="building" color="255,230,230" fill="1" layer="-1.00" shape="8846.473575,32531.942118 8882.513081,32511.205979 8848.953122,32448.957822 8811.927086,32465.876730 8821.106087,32486.252487 8836.189072,32480.941172 8849.316143,32503.193223 8835.890614,32512.066342 8846.473575,32531.942118"/>
    <poly id="1171265306" type="building" color="255,230,230" fill="1" layer="-1.00" shape="8791.064635,32557.818434 8795.018099,32563.624028 8820.418886,32550.417813 8818.104754,32542.462678 8827.753628,32536.284347 8796.996142,32484.215544 8786.529394,32489.011442 8782.656467,32481.689348 8758.235296,32493.776360 8760.469816,32503.912099 8757.437108,32506.782999 8785.881130,32558.899158 8791.064635,32557.818434"/>
    <poly id="1171265502" type="building" color="255,230,230" fill="1" layer="-1.00" shape="8310.720901,32698.708798 8338.696337,32687.977567 8288.438648,32577.826995 8260.118569,32585.957683 8310.720901,32698.708798"/>
    <poly id="1171265503" type="building" color="255,230,230" fill="1" layer="-1.00" shape="8353.134549,32679.755656 8373.408270,32671.426022 8328.499411,32560.127826 8302.202980,32567.746463 8353.134549,32679.755656"/>
    <poly id="1171267585" type="pipeline" color="255,230,230" fill="0" layer="-1.00" shape="8590.932545,32457.247251 8630.563692,32427.108394 8701.345806,32260.783764"/>
    <poly id="1171267585#1" type="water" color="181,209,209" fill="0" layer="-4.00" shape="8590.932545,32457.247251 8630.563692,32427.108394 8701.345806,32260.783764"/>
    <poly id="1171267586" type="water" color="181,209,209" fill="0" layer="-4.00" shape="8701.345806,32260.783764 8734.463505,32225.551505 8888.358632,32153.506837 9058.877727,32083.909556 9216.816914,32013.810728 9310.626731,31968.680839 9352.540195,31912.983529 9436.760169,31762.306499 9618.635100,31423.104026 9704.758082,31270.300894 9752.948848,31225.631839 10017.907904,31054.645257 10267.442392,30893.644445 10498.403568,30753.070229 10721.545812,30609.863765 10798.346750,30558.255703 10871.457438,30462.345311 11015.458470,30251.977486 11060.781016,30204.681717 11159.682572,30154.122144 11316.692776,30086.823947 11478.442508,30016.688124 11688.108533,29922.700042 11856.457070,29856.611391 12598.214478,29897.953935 12894.206463,29922.805016 13127.837533,29894.622831"/>
    <poly id="1171271401" type="leisure" color="207,245,201" fill="1" layer="-2.00" shape="8877.705567,32659.730333 8827.706394,32569.844258 8906.280236,32527.068136 8958.821904,32618.412057 8877.705567,32659.730333"/>
    <poly id="1171271987" type="leisure" color="207,245,201" fill="1" layer="-2.00" shape="8865.222595,32450.241775 8854.173411,32429.337248 8890.864307,32408.921234 8902.750427,32430.079227 8865.222595,32450.241775"/>
    <poly id="1171273740" type="building" color="255,230,230" fill="1" layer="-1.00" shape="8393.964875,32547.064361 8379.732278,32517.564314 8387.009440,32514.288972 8399.909309,32543.558437 8393.964875,32547.064361"/>
    <poly id="1171274080" type="building" color="255,230,230" fill="1" layer="-1.00" shape="10073.267500,31604.513946 10054.828073,31571.022108 9938.838940,31641.700208 9941.970587,31651.159758 9893.531893,31687.228338 9915.233778,31727.334757 9932.519931,31715.557626 9939.472957,31724.702319 9960.675829,31714.425480 9956.725543,31702.908236 9993.648282,31675.654166 9982.593859,31657.947692 10011.521074,31638.064550 10019.854585,31644.396093 10044.557459,31624.706613 10073.267500,31604.513946"/>
    <poly id="1172656582" type="building" color="255,230,230" fill="1" layer="-1.00" shape="7234.312058,33893.339470 7231.598962,33902.519293 7322.275088,33915.458794 7336.720252,33835.179478 7249.759570,33820.784472 7247.501280,33830.240341 7321.663659,33843.204009 7310.071370,33903.843520 7234.312058,33893.339470"/>
    <poly id="1172657872" type="leisure" color="207,245,201" fill="1" layer="-2.00" shape="7261.843247,33601.863566 7261.198930,33577.945318 7276.184022,33577.381058 7277.272920,33601.641783 7261.843247,33601.863566"/>
    <poly id="1172657873" type="building" color="255,230,230" fill="1" layer="-1.00" shape="7285.430436,33600.556216 7291.658694,33600.890247 7292.019399,33593.285610 7296.986889,33593.101261 7296.793037,33587.655805 7292.361371,33586.998160 7292.453565,33579.404983 7285.512927,33579.249089 7285.430436,33600.556216"/>
    <poly id="1172658047" type="amenity" color="237,199,199" fill="1" layer="-1.00" shape="7180.523959,33336.502907 7037.279363,33390.130608 7060.179225,33503.848568 7188.021890,33491.241633 7270.739504,33420.746558 7180.523959,33336.502907"/>
    <poly id="1193889767" type="historic" color="128,255,128" fill="1" layer="-1.00" shape="1929.625841,36204.335070 1921.692022,36179.621992 1932.846892,36175.229790 1941.034789,36197.684412 1929.625841,36204.335070"/>
    <poly id="1193889770" type="building" color="255,230,230" fill="1" layer="-1.00" shape="1871.834572,36161.415378 1860.854077,36165.154258 1865.172435,36177.676177 1870.351311,36174.932876 1878.937811,36195.051263 1890.858281,36191.476731 1892.193677,36199.034212 1901.200495,36194.557311 1899.509109,36190.011144 1901.602675,36188.524172 1908.894059,36183.341974 1905.085731,36167.310361 1907.014554,36160.355774 1903.619756,36150.322625 1895.984158,36153.601638 1899.194423,36164.376717 1892.764339,36166.170360 1891.542890,36158.811910 1883.831143,36159.943748 1885.518537,36167.998682 1876.231719,36171.823046 1871.834572,36161.415378"/>
    <poly id="126683755" type="water" color="181,209,209" fill="0" layer="-4.00" shape="1240.094335,35940.486160 1255.019507,35886.277593 1254.025465,35828.777776 1256.619059,35812.845206 1288.629019,35721.735536 1291.238696,35703.290362 1285.055443,35687.772426 1276.631338,35672.280756 1225.547110,35622.898028 1207.578518,35617.241894 1190.224829,35614.639591 1180.912086,35604.517907 1175.963168,35592.030544 1235.229932,35408.081983 1320.585592,35151.940307 1393.876537,35005.533671 1344.385569,34761.826621 1282.342940,34359.662146 1379.695982,33957.193966 1550.953840,33737.456507 1807.998473,33493.170626 2001.932020,33425.701508 2093.226111,33364.217904 2120.966104,33322.904543 2154.380071,33237.306663 2236.336379,33029.137221 2223.447608,32675.606706 2039.013980,32395.523850 1964.884706,32090.860655 1719.214203,31859.648743 1375.451393,31640.817559 1325.793743,31311.706337 1374.446563,31092.149068 1631.753204,30969.748385 1950.785614,31066.720042 2134.648874,31017.622909 2244.804826,30895.495340 2158.464991,30615.204269 1912.808281,30408.362463 1716.213615,30201.424530 1544.204626,30031.025907 1421.028367,29738.608383 1347.076449,29543.637889 1101.380415,29324.599960 1015.092139,29093.061109 1112.742626,28836.798115 1333.026729,28568.113175 1430.819223,28385.015312 1319.735672,28007.171854 1171.844782,27629.385914 1011.818155,27324.786986 716.856210,27020.441333 471.158785,26825.774995 249.938448,26606.659779 -69.427947,26387.735559 -131.208193,26156.123038 -144.106349,25826.836461 76.362070,25643.462285 309.563076,25703.995561 481.769502,25947.609895 739.687348,26105.683120 801.250530,26227.532532 1181.561136,26239.026017 1352.744855,25933.796147 1425.812908,25640.944427 1388.605316,25421.457043 1265.503366,25189.940566 909.438209,25032.029575 725.134370,24886.002422 503.832499,24630.269300 417.303921,24288.890881 292.420908,23832.782930 425.570859,23279.781069 846.526397,22840.603336 1267.564593,22439.534838 1707.909775,22095.622878 1783.982110,21752.374163 1879.162622,21370.949789 1724.816027,20837.461198 1417.573652,20590.183362 1263.762263,20361.700958 1340.077261,20151.858464"/>
    <poly id="1291335334" type="building" color="255,230,230" fill="1" layer="-1.00" shape="3275.266253,33980.009520 3307.570164,33955.094095 3315.581437,33965.363124 3283.277535,33990.278534 3275.266253,33980.009520"/>
    <poly id="1292006621" type="building" color="255,230,230" fill="1" layer="-1.00" shape="2197.182357,36419.351155 2202.674310,36418.466937 2205.012967,36432.818806 2199.510693,36433.703042 2197.182357,36419.351155"/>
    <poly id="1314106578" type="building" color="255,230,230" fill="1" layer="-1.00" shape="4315.627459,35987.170144 4322.900852,35964.290364 4335.330429,35968.442744 4328.479582,35990.823733 4315.627459,35987.170144"/>
    <poly id="1314106579" type="building" color="255,230,230" fill="1" layer="-1.00" shape="4330.242370,35988.983435 4336.003563,35969.603841 4347.091809,35974.433627 4340.750938,35992.972956 4330.242370,35988.983435"/>
    <poly id="1314106580" type="building" color="255,230,230" fill="1" layer="-1.00" shape="4345.773027,35988.791809 4350.625507,35975.678560 4361.549196,35980.918167 4356.282686,35993.445457 4345.773027,35988.791809"/>
    <poly id="1314106581" type="building" color="255,230,230" fill="1" layer="-1.00" shape="4357.790214,35993.365493 4361.553734,35983.674247 4367.185205,35985.834426 4365.263094,35991.261218 4368.622203,35993.093080 4366.945048,35996.770625 4357.790214,35993.365493"/>
    <poly id="1314106583" type="building" color="255,230,230" fill="1" layer="-1.00" shape="4295.805927,36190.511420 4303.998622,36186.634945 4310.668568,36198.633401 4301.919153,36203.053155 4295.805927,36190.511420"/>
    <poly id="1314106584" type="building" color="255,230,230" fill="1" layer="-1.00" shape="4342.884908,36178.778499 4339.202416,36181.208597 4342.895779,36185.375384 4346.507646,36183.952647 4342.884908,36178.778499"/>
    <poly id="1314106585" type="building" color="255,230,230" fill="1" layer="-1.00" shape="4337.985830,36169.843121 4341.137849,36177.619172 4333.758490,36180.022159 4330.451701,36172.323845 4337.985830,36169.843121"/>
    <poly id="1314106586" type="building" color="255,230,230" fill="1" layer="-1.00" shape="4360.191192,36203.477306 4350.161533,36201.767120 4349.209664,36213.180446 4358.472803,36213.452971 4360.191192,36203.477306"/>
    <poly id="1314106587" type="building" color="255,230,230" fill="1" layer="-1.00" shape="4341.392570,36206.862071 4340.226395,36201.019756 4346.585485,36199.858139 4347.843974,36205.323969 4341.392570,36206.862071"/>
    <poly id="1314106588" type="building" color="255,230,230" fill="1" layer="-1.00" shape="4356.207003,36185.740855 4350.432816,36190.930485 4360.379498,36198.684279 4365.285640,36193.108679 4356.207003,36185.740855"/>
    <poly id="1314106589" type="building" color="255,230,230" fill="1" layer="-1.00" shape="4311.859038,36194.159710 4320.342496,36191.267872 4323.151312,36203.826134 4315.730517,36206.140649 4311.859038,36194.159710"/>
    <poly id="1314106590" type="building" color="255,230,230" fill="1" layer="-1.00" shape="4341.021660,36219.901528 4343.812345,36215.203830 4352.885118,36219.018627 4350.960744,36223.050778 4341.021660,36219.901528"/>
    <poly id="1314106591" type="building" color="255,230,230" fill="1" layer="-1.00" shape="4326.167434,36216.860006 4325.581095,36211.968638 4333.202047,36212.055690 4333.394873,36216.272520 4326.167434,36216.860006"/>
    <poly id="1314106592" type="building" color="255,230,230" fill="1" layer="-1.00" shape="4342.580354,36244.615209 4334.174915,36244.706544 4333.902549,36254.879064 4341.875959,36255.806755 4342.580354,36244.615209"/>
    <poly id="1314106593" type="building" color="255,230,230" fill="1" layer="-1.00" shape="4397.589138,36088.058515 4394.295937,36094.893274 4409.316686,36098.665117 4412.484721,36091.066831 4397.589138,36088.058515"/>
    <poly id="1314106594" type="building" color="255,230,230" fill="1" layer="-1.00" shape="4399.229069,36080.584495 4404.169224,36064.261216 4412.321512,36067.158865 4411.181307,36070.824454 4414.104504,36071.328807 4419.197056,36072.327684 4415.911755,36083.977278 4399.229069,36080.584495"/>
    <poly id="1314106595" type="building" color="255,230,230" fill="1" layer="-1.00" shape="4436.436645,36106.722798 4443.155015,36091.647366 4451.049958,36095.054614 4445.973404,36103.796093 4449.673340,36105.682755 4450.556428,36102.648502 4449.664203,36100.115251 4451.311023,36096.825166 4457.428778,36099.593353 4451.078204,36112.266283 4436.436645,36106.722798"/>
    <poly id="1314106596" type="building" color="255,230,230" fill="1" layer="-1.00" shape="4451.523918,36069.241798 4446.830883,36078.868137 4454.724779,36081.633408 4449.649471,36091.138618 4452.326684,36092.772382 4451.049958,36095.054614 4457.166897,36097.324714 4459.073112,36094.786871 4460.468622,36095.670072 4465.543535,36085.921356 4469.490688,36087.431284 4473.553409,36077.551407 4451.523918,36069.241798"/>
    <poly id="1314106597" type="building" color="255,230,230" fill="1" layer="-1.00" shape="4407.933732,36036.317813 4409.648862,36024.327671 4424.590843,36024.114952 4422.113750,36037.445648 4407.933732,36036.317813"/>
    <poly id="1314106598" type="building" color="255,230,230" fill="1" layer="-1.00" shape="4281.556616,36209.871848 4283.304099,36217.539522 4274.526772,36217.554022 4273.358981,36210.748744 4281.556616,36209.871848"/>
    <poly id="1314106599" type="building" color="255,230,230" fill="1" layer="-1.00" shape="4334.630031,36226.376143 4334.740029,36236.725130 4329.824731,36236.733234 4329.716300,36227.336146 4334.630031,36226.376143"/>
    <poly id="1314106600" type="building" color="255,230,230" fill="1" layer="-1.00" shape="4232.379582,36245.383844 4234.803842,36256.404189 4209.637830,36262.101925 4207.595771,36251.169500 4232.379582,36245.383844"/>
    <poly id="1314106601" type="building" color="255,230,230" fill="1" layer="-1.00" shape="4302.312232,36253.514390 4302.529166,36266.076928 4324.224589,36266.041133 4324.493151,36253.566344 4302.312232,36253.514390"/>
    <poly id="1314106602" type="building" color="255,230,230" fill="1" layer="-1.00" shape="4276.293034,36267.835892 4275.218379,36254.898438 4297.289237,36250.833005 4297.123794,36263.208007 4276.293034,36267.835892"/>
    <poly id="1314106603" type="building" color="255,230,230" fill="1" layer="-1.00" shape="4433.441734,36049.967796 4437.087607,36037.786320 4447.026948,36041.035248 4443.091294,36052.829796 4433.441734,36049.967796"/>
    <poly id="1314106604" type="building" color="255,230,230" fill="1" layer="-1.00" shape="4436.888098,36035.772157 4443.506804,36016.579362 4453.642049,36019.639806 4447.313089,36039.208455 4436.888098,36035.772157"/>
    <poly id="1314106605" type="building" color="255,230,230" fill="1" layer="-1.00" shape="4448.655519,36039.206252 4453.744104,36025.196089 4461.658060,36027.584998 4457.056226,36042.457712 4448.655519,36039.206252"/>
    <poly id="624188567" type="building" color="255,230,230" fill="1" layer="-1.00" shape="3539.510699,33729.474773 3596.931572,33697.566273 3584.749176,33675.881370 3527.317920,33707.789930 3539.510699,33729.474773"/>
    <poly id="624188568" type="building" color="255,230,230" fill="1" layer="-1.00" shape="3501.770178,33691.662086 3578.711461,33653.942555 3567.415355,33631.160371 3490.463658,33668.879974 3501.770178,33691.662086"/>
    <poly id="735439392" type="building" color="255,230,230" fill="1" layer="-1.00" shape="1508.003508,35017.965247 1520.624399,35018.606324 1521.421918,35002.909537 1508.801014,35002.268459 1508.003508,35017.965247"/>
    <poly id="754801684" type="building" color="255,230,230" fill="1" layer="-1.00" shape="2154.198072,34669.099518 2155.313327,34697.975582 2177.102473,34697.150832 2175.997584,34668.274748 2154.198072,34669.099518"/>
    <poly id="756794644" type="building" color="255,230,230" fill="1" layer="-1.00" shape="2410.018386,34991.417251 2414.266625,35011.078694 2423.908505,35009.025014 2419.660258,34989.352500 2410.018386,34991.417251"/>
    <poly id="758304493" type="building" color="255,230,230" fill="1" layer="-1.00" shape="3925.848327,35674.343271 3939.058907,35669.838370 3935.613742,35659.849165 3922.403155,35664.354069 3925.848327,35674.343271"/>
    <poly id="758651284" type="building" color="255,230,230" fill="1" layer="-1.00" shape="1923.340898,34875.622287 1928.219241,34877.794029 1933.721923,34876.843295 1933.962634,34878.613843 1945.288122,34876.700736 1947.010295,34886.814371 1939.525340,34888.067519 1940.120259,34891.553069 1949.019614,34890.064936 1950.136461,34896.648765 1956.423822,34895.597010 1952.948088,34875.137354 1951.173306,34864.481450 1926.911715,34868.554073 1927.151769,34869.959357 1922.154916,34870.798497 1923.340898,34875.622287"/>
    <poly id="774672388" type="building" color="255,230,230" fill="1" layer="-1.00" shape="4784.561482,35017.899548 4788.901542,35025.939402 4801.974656,35018.967155 4797.644928,35010.927281 4784.561482,35017.899548"/>
    <poly id="776198743" type="building" color="255,230,230" fill="1" layer="-1.00" shape="2281.700159,34884.655382 2295.022189,34878.820682 2292.160412,34872.361685 2302.366070,34867.893969 2319.920435,34907.577053 2299.323395,34916.579212 2295.217356,34907.299923 2292.328000,34908.566879 2293.707034,34911.674715 2288.681613,34913.875232 2283.103194,34901.266904 2290.326607,34898.110578 2292.970646,34904.082942 2296.778411,34902.415884 2299.443199,34908.443555 2309.989377,34903.831346 2300.927034,34883.337264 2284.333817,34890.594557 2281.700159,34884.655382"/>
    <poly id="824528330" type="building" color="255,230,230" fill="1" layer="-1.00" shape="3868.714094,33717.651759 3876.158530,33728.785367 3886.402838,33722.027426 3878.958387,33710.882744 3868.714094,33717.651759"/>
    <poly id="824528333" type="building" color="255,230,230" fill="1" layer="-1.00" shape="1785.836237,35099.390405 1798.733538,35098.736172 1797.727461,35079.190776 1784.830144,35079.845010 1785.836237,35099.390405"/>
    <poly id="824528343" type="building" color="255,230,230" fill="1" layer="-1.00" shape="2383.595999,35262.324539 2387.920173,35272.400408 2405.215126,35265.064495 2400.901288,35254.988603 2383.595999,35262.324539"/>
    <poly id="824528345" type="building" color="255,230,230" fill="1" layer="-1.00" shape="2729.710611,34717.393422 2737.848003,34734.823347 2746.835819,34730.679040 2738.708743,34713.238024 2729.710611,34717.393422"/>
    <poly id="824528351" type="building" color="255,230,230" fill="1" layer="-1.00" shape="2048.471817,35127.153677 2052.497750,35137.783423 2071.734432,35130.587559 2067.708510,35119.957809 2048.471817,35127.153677"/>
    <poly id="824528357" type="building" color="255,230,230" fill="1" layer="-1.00" shape="2043.859148,35025.396908 2047.673172,35033.016363 2062.479413,35025.684538 2058.665414,35018.076149 2043.859148,35025.396908"/>
    <poly id="824528366" type="building" color="255,230,230" fill="1" layer="-1.00" shape="2418.621615,35528.983474 2432.907469,35525.371970 2423.975180,35490.543695 2409.689317,35494.166275 2418.621615,35528.983474"/>
    <poly id="824528372" type="building" color="255,230,230" fill="1" layer="-1.00" shape="2260.076919,35582.405266 2264.888588,35593.686720 2279.974952,35587.328630 2275.163292,35576.047173 2260.076919,35582.405266"/>
    <poly id="824528373" type="building" color="255,230,230" fill="1" layer="-1.00" shape="4297.443430,36006.448492 4307.309312,36008.955857 4314.460931,35981.128597 4304.595033,35978.621228 4297.443430,36006.448492"/>
    <poly id="824528377" type="building" color="255,230,230" fill="1" layer="-1.00" shape="2097.390585,34832.518672 2107.921227,34830.773133 2105.405536,34815.768566 2094.874884,34817.514107 2097.390585,34832.518672"/>
    <poly id="824528381" type="building" color="255,230,230" fill="1" layer="-1.00" shape="2216.223222,35422.320134 2220.685850,35434.720127 2250.996515,35423.918514 2246.533928,35411.529581 2216.223222,35422.320134"/>
    <poly id="824528382" type="building" color="255,230,230" fill="1" layer="-1.00" shape="6266.467621,33462.325147 6283.031640,33460.872055 6281.739316,33446.451664 6286.086856,33446.068709 6285.435371,33438.753370 6281.087828,33439.136325 6280.352232,33430.847079 6263.788199,33432.311241 6266.467621,33462.325147"/>
    <poly id="824528383" type="building" color="255,230,230" fill="1" layer="-1.00" shape="2161.470001,34884.050420 2172.245328,34886.333468 2179.384168,34853.136976 2168.608819,34850.853922 2161.470001,34884.050420"/>
    <poly id="824528387" type="building" color="255,230,230" fill="1" layer="-1.00" shape="2098.072312,34890.328920 2122.608467,34901.198723 2112.930417,34911.919390 2086.736343,34897.931214 2098.072312,34890.328920"/>
    <poly id="824528388" type="building" color="255,230,230" fill="1" layer="-1.00" shape="7025.556981,33879.688945 7032.568740,33879.136229 7032.800184,33882.002650 7037.694993,33881.619092 7037.463550,33878.752671 7040.685440,33878.493338 7039.980474,33869.683789 7024.852007,33870.879396 7025.556981,33879.688945"/>
    <poly id="824528395" type="building" color="255,230,230" fill="1" layer="-1.00" shape="3434.897985,35092.509090 3440.009119,35104.188846 3456.334481,35097.143526 3451.233665,35085.452679 3434.897985,35092.509090"/>
    <poly id="824528402" type="building" color="255,230,230" fill="1" layer="-1.00" shape="2899.353095,35897.290441 2912.008039,35894.202427 2906.984920,35873.833797 2894.329962,35876.921814 2899.353095,35897.290441"/>
    <poly id="944192334" type="building" color="255,230,230" fill="1" layer="-1.00" shape="5215.618035,35286.705948 5228.712628,35286.762585 5228.796438,35268.045430 5215.701830,35267.988793 5215.618035,35286.705948"/>
    <poly id="944193629" type="building" color="255,230,230" fill="1" layer="-1.00" shape="5653.594587,34971.566637 5668.438669,34967.547658 5663.401272,34949.159514 5648.557192,34953.189567 5653.594587,34971.566637"/>
    <poly id="944194784" type="building" color="255,230,230" fill="1" layer="-1.00" shape="6314.522286,34791.058143 6340.911686,34786.490932 6330.421119,34726.636854 6304.031639,34731.215150 6314.522286,34791.058143"/>
    <poi id="6888415023" type="amenity" color="237,199,199" layer="4.00" x="1514.36" y="35010.53"/>
    <poi id="7051034541" type="amenity" color="237,199,199" layer="4.00" x="2163.13" y="34682.53"/>
    <poi id="7068377986" type="amenity" color="237,199,199" layer="4.00" x="2417.15" y="35000.62"/>
    <poi id="7081842626" type="amenity" color="237,199,199" layer="4.00" x="3928.56" y="35667.03"/>
    <poi id="7085654949" type="amenity" color="237,199,199" layer="4.00" x="1941.58" y="34868.84"/>
    <poi id="7227752883" type="amenity" color="237,199,199" layer="4.00" x="4790.18" y="35020.16"/>
    <poi id="7242147679" type="amenity" color="237,199,199" layer="4.00" x="2311.22" y="34905.95"/>
    <poi id="7699151609" type="amenity" color="237,199,199" layer="4.00" x="2062.37" y="35127.24"/>
    <poi id="7699151613" type="amenity" color="237,199,199" layer="4.00" x="2115.31" y="34903.12"/>
    <poi id="7699151615" type="amenity" color="237,199,199" layer="4.00" x="2054.03" y="35025.26"/>
    <poi id="7699151616" type="amenity" color="237,199,199" layer="4.00" x="4305.06" y="35995.59"/>
    <poi id="7699151621" type="clinic" color="237,199,199" layer="3.00" x="2391.18" y="35266.42"/>
    <poi id="7699151622" type="amenity" color="237,199,199" layer="4.00" x="2740.38" y="34728.69"/>
    <poi id="7699151625" type="clinic" color="237,199,199" layer="3.00" x="2099.09" y="34824.39"/>
    <poi id="7699151630" type="clinic" color="237,199,199" layer="3.00" x="3447.72" y="35092.92"/>
    <poi id="7699151634" type="amenity" color="237,199,199" layer="4.00" x="1790.58" y="35089.50"/>
    <poi id="7699151635" type="amenity" color="237,199,199" layer="4.00" x="2244.64" y="35427.47"/>
    <poi id="7699151637" type="amenity" color="237,199,199" layer="4.00" x="2425.02" y="35520.14"/>
    <poi id="7699151641" type="clinic" color="237,199,199" layer="3.00" x="2269.56" y="35584.62"/>
    <poi id="7699151644" type="clinic" color="237,199,199" layer="3.00" x="2902.94" y="35884.83"/>
    <poi id="7699151654" type="clinic" color="237,199,199" layer="3.00" x="3878.02" y="33719.99"/>
    <poi id="7699151661" type="amenity" color="237,199,199" layer="4.00" x="2168.80" y="34864.36"/>
</additional>
